README.txt
setup.py
mo_hg/__init__.py
mo_hg/cache.py
mo_hg/hg_branches.py
mo_hg/hg_mozilla_org.py
mo_hg/parse.py
mo_hg/rate_logger.py
mo_hg/relay_app.py
mo_hg.egg-info/PKG-INFO
mo_hg.egg-info/SOURCES.txt
mo_hg.egg-info/dependency_links.txt
mo_hg.egg-info/not-zip-safe
mo_hg.egg-info/requires.txt
mo_hg.egg-info/top_level.txt
mo_hg/repos/__init__.py
mo_hg/repos/changesets.py
mo_hg/repos/pushs.py
mo_hg/repos/revisions.py
tests/__init__.py
tests/scan_hg.py
tests/test.py