Metadata-Version: 1.1
Name: mo-hg
Version: 2.18.18240
Summary: Fast cache for Mozilla's Mercurial repository
Home-page: https://github.com/klahnakoski/mo-hg
Author: Kyle Lahnakoski
Author-email: kyle@lahnakoski.com
License: MPL 2.0
Platform: UNKNOWN
Classifier: Development Status :: 4 - Beta
Classifier: Topic :: Software Development :: Libraries
Classifier: Topic :: Software Development :: Libraries :: Python Modules
Classifier: License :: OSI Approved :: Mozilla Public License 2.0 (MPL 2.0)
